{
  "version": "https://jsonfeed.org/version/1.1",
  "title": "OpenWeather",
  "feed_url": "https://raw.githubusercontent.com/trvny/feeds/main/feedseek/feeds/feed_openweather.json",
  "home_page_url": "https://openweathermap.org/city/3101547",
  "description": "Daily forecast aggregated from OpenWeather's 5-day/3-hour data",
  "favicon": "https://openweathermap.org/favicon.ico",
  "items": [
    {
      "id": "urn:openweather:chrzanów-pl:2026-07-29",
      "url": "https://openweathermap.org/city/3101547",
      "title": "Chrzanów, PL: Wed 29 Jul — Clear sky, 14–14°C",
      "content_html": "<p><strong>Clear sky</strong> · High 14°C · Low 14°C</p>\n<ul>\n<li>Chance of precipitation: 0%</li>\n<li>Feels like (midday): 14°C</li>\n<li>Wind: up to 1.5 m/s</li>\n<li>Humidity: 74%</li>\n</ul>\n<p><em>Partial day (forecast window does not cover all hours).</em></p>",
      "date_published": "2026-07-28T22:00:00Z",
      "date_modified": "2026-07-24T02:49:59Z",
      "tags": [
        "weather"
      ]
    },
    {
      "id": "urn:openweather:chrzanów-pl:2026-07-28",
      "url": "https://openweathermap.org/city/3101547",
      "title": "Chrzanów, PL: Tue 28 Jul — Scattered clouds, 13–24°C",
      "content_html": "<p><strong>Scattered clouds</strong> · High 24°C · Low 13°C</p>\n<ul>\n<li>Chance of precipitation: 0%</li>\n<li>Feels like (midday): 22°C</li>\n<li>Wind: up to 3.0 m/s</li>\n<li>Humidity: 66%</li>\n</ul>",
      "date_published": "2026-07-27T22:00:00Z",
      "date_modified": "2026-07-24T02:49:59Z",
      "tags": [
        "weather"
      ]
    },
    {
      "id": "urn:openweather:chrzanów-pl:2026-07-27",
      "url": "https://openweathermap.org/city/3101547",
      "title": "Chrzanów, PL: Mon 27 Jul — Light rain, 15–19°C",
      "content_html": "<p><strong>Light rain</strong> · High 19°C · Low 15°C</p>\n<ul>\n<li>Chance of precipitation: 100%</li>\n<li>Feels like (midday): 18°C</li>\n<li>Wind: up to 4.4 m/s</li>\n<li>Humidity: 84%</li>\n<li>Rain: 7.7 mm</li>\n</ul>",
      "date_published": "2026-07-26T22:00:00Z",
      "date_modified": "2026-07-24T02:49:59Z",
      "tags": [
        "weather"
      ]
    },
    {
      "id": "urn:openweather:chrzanów-pl:2026-07-26",
      "url": "https://openweathermap.org/city/3101547",
      "title": "Chrzanów, PL: Sun 26 Jul — Broken clouds, 14–29°C",
      "content_html": "<p><strong>Broken clouds</strong> · High 29°C · Low 14°C</p>\n<ul>\n<li>Chance of precipitation: 0%</li>\n<li>Feels like (midday): 28°C</li>\n<li>Wind: up to 4.6 m/s</li>\n<li>Humidity: 51%</li>\n</ul>",
      "date_published": "2026-07-25T22:00:00Z",
      "date_modified": "2026-07-24T01:31:02Z",
      "tags": [
        "weather"
      ]
    },
    {
      "id": "urn:openweather:chrzanów-pl:2026-07-25",
      "url": "https://openweathermap.org/city/3101547",
      "title": "Chrzanów, PL: Sat 25 Jul — Broken clouds, 12–24°C",
      "content_html": "<p><strong>Broken clouds</strong> · High 24°C · Low 12°C</p>\n<ul>\n<li>Chance of precipitation: 0%</li>\n<li>Feels like (midday): 23°C</li>\n<li>Wind: up to 2.7 m/s</li>\n<li>Humidity: 58%</li>\n</ul>",
      "date_published": "2026-07-24T22:00:00Z",
      "date_modified": "2026-07-24T01:31:02Z",
      "tags": [
        "weather"
      ]
    },
    {
      "id": "urn:openweather:chrzanów-pl:2026-07-24",
      "url": "https://openweathermap.org/city/3101547",
      "title": "Chrzanów, PL: Fri 24 Jul — Broken clouds, 11–18°C",
      "content_html": "<p><strong>Broken clouds</strong> · High 18°C · Low 11°C</p>\n<ul>\n<li>Chance of precipitation: 34%</li>\n<li>Feels like (midday): 15°C</li>\n<li>Wind: up to 4.9 m/s</li>\n<li>Humidity: 69%</li>\n<li>Rain: 0.7 mm</li>\n</ul>",
      "date_published": "2026-07-23T22:00:00Z",
      "date_modified": "2026-07-24T01:31:02Z",
      "tags": [
        "weather"
      ]
    },
    {
      "id": "urn:openweather:chrzanów-pl:2026-07-23",
      "url": "https://openweathermap.org/city/3101547",
      "title": "Chrzanów, PL: Thu 23 Jul — Light rain, 12–12°C",
      "content_html": "<p><strong>Light rain</strong> · High 12°C · Low 12°C</p>\n<ul>\n<li>Chance of precipitation: 96%</li>\n<li>Feels like (midday): 12°C</li>\n<li>Wind: up to 3.4 m/s</li>\n<li>Humidity: 88%</li>\n<li>Rain: 1.0 mm</li>\n</ul>\n<p><em>Partial day (forecast window does not cover all hours).</em></p>",
      "date_published": "2026-07-22T22:00:00Z",
      "date_modified": "2026-07-23T19:23:16Z",
      "tags": [
        "weather"
      ]
    },
    {
      "id": "urn:openweather:chrzanów-pl:2026-07-22",
      "url": "https://openweathermap.org/city/3101547",
      "title": "Chrzanów, PL: Wed 22 Jul — Broken clouds, 16–16°C",
      "content_html": "<p><strong>Broken clouds</strong> · High 16°C · Low 16°C</p>\n<ul>\n<li>Chance of precipitation: 0%</li>\n<li>Feels like (midday): 16°C</li>\n<li>Wind: up to 2.8 m/s</li>\n<li>Humidity: 60%</li>\n</ul>\n<p><em>Partial day (forecast window does not cover all hours).</em></p>",
      "date_published": "2026-07-21T22:00:00Z",
      "date_modified": "2026-07-22T19:26:43Z",
      "tags": [
        "weather"
      ]
    },
    {
      "id": "urn:openweather:chrzanów-pl:2026-07-21",
      "url": "https://openweathermap.org/city/3101547",
      "title": "Chrzanów, PL: Tue 21 Jul — Broken clouds, 15–15°C",
      "content_html": "<p><strong>Broken clouds</strong> · High 15°C · Low 15°C</p>\n<ul>\n<li>Chance of precipitation: 0%</li>\n<li>Feels like (midday): 15°C</li>\n<li>Wind: up to 2.1 m/s</li>\n<li>Humidity: 81%</li>\n</ul>\n<p><em>Partial day (forecast window does not cover all hours).</em></p>",
      "date_published": "2026-07-20T22:00:00Z",
      "date_modified": "2026-07-21T19:28:49Z",
      "tags": [
        "weather"
      ]
    },
    {
      "id": "urn:openweather:chrzanów-pl:2026-07-20",
      "url": "https://openweathermap.org/city/3101547",
      "title": "Chrzanów, PL: Mon 20 Jul — Scattered clouds, 18–18°C",
      "content_html": "<p><strong>Scattered clouds</strong> · High 18°C · Low 18°C</p>\n<ul>\n<li>Chance of precipitation: 0%</li>\n<li>Feels like (midday): 18°C</li>\n<li>Wind: up to 2.3 m/s</li>\n<li>Humidity: 69%</li>\n</ul>\n<p><em>Partial day (forecast window does not cover all hours).</em></p>",
      "date_published": "2026-07-19T22:00:00Z",
      "date_modified": "2026-07-20T18:08:06Z",
      "tags": [
        "weather"
      ]
    },
    {
      "id": "urn:openweather:chrzanów-pl:2026-07-19",
      "url": "https://openweathermap.org/city/3101547",
      "title": "Chrzanów, PL: Sun 19 Jul — Overcast clouds, 16–16°C",
      "content_html": "<p><strong>Overcast clouds</strong> · High 16°C · Low 16°C</p>\n<ul>\n<li>Chance of precipitation: 0%</li>\n<li>Feels like (midday): 16°C</li>\n<li>Wind: up to 4.0 m/s</li>\n<li>Humidity: 93%</li>\n</ul>\n<p><em>Partial day (forecast window does not cover all hours).</em></p>",
      "date_published": "2026-07-18T22:00:00Z",
      "date_modified": "2026-07-19T20:54:58Z",
      "tags": [
        "weather"
      ]
    },
    {
      "id": "urn:openweather:chrzanów-pl:2026-07-18",
      "url": "https://openweathermap.org/city/3101547",
      "title": "Chrzanów, PL: Sat 18 Jul — Light rain, 19–19°C",
      "content_html": "<p><strong>Light rain</strong> · High 19°C · Low 19°C</p>\n<ul>\n<li>Chance of precipitation: 39%</li>\n<li>Feels like (midday): 19°C</li>\n<li>Wind: up to 1.0 m/s</li>\n<li>Humidity: 90%</li>\n<li>Rain: 0.2 mm</li>\n</ul>\n<p><em>Partial day (forecast window does not cover all hours).</em></p>",
      "date_published": "2026-07-17T22:00:00Z",
      "date_modified": "2026-07-18T20:54:19Z",
      "tags": [
        "weather"
      ]
    },
    {
      "id": "urn:openweather:chrzanów-pl:2026-07-17",
      "url": "https://openweathermap.org/city/3101547",
      "title": "Chrzanów, PL: Fri 17 Jul — Moderate rain, 22–22°C",
      "content_html": "<p><strong>Moderate rain</strong> · High 22°C · Low 22°C</p>\n<ul>\n<li>Chance of precipitation: 100%</li>\n<li>Feels like (midday): 23°C</li>\n<li>Wind: up to 2.9 m/s</li>\n<li>Humidity: 84%</li>\n<li>Rain: 4.4 mm</li>\n</ul>\n<p><em>Partial day (forecast window does not cover all hours).</em></p>",
      "date_published": "2026-07-16T22:00:00Z",
      "date_modified": "2026-07-17T19:14:42Z",
      "tags": [
        "weather"
      ]
    },
    {
      "id": "urn:openweather:chrzanów-pl:2026-07-16",
      "url": "https://openweathermap.org/city/3101547",
      "title": "Chrzanów, PL: Thu 16 Jul — Scattered clouds, 23–23°C",
      "content_html": "<p><strong>Scattered clouds</strong> · High 23°C · Low 23°C</p>\n<ul>\n<li>Chance of precipitation: 0%</li>\n<li>Feels like (midday): 23°C</li>\n<li>Wind: up to 1.3 m/s</li>\n<li>Humidity: 77%</li>\n</ul>\n<p><em>Partial day (forecast window does not cover all hours).</em></p>",
      "date_published": "2026-07-15T22:00:00Z",
      "date_modified": "2026-07-16T19:16:11Z",
      "tags": [
        "weather"
      ]
    },
    {
      "id": "urn:openweather:chrzanów-pl:2026-07-15",
      "url": "https://openweathermap.org/city/3101547",
      "title": "Chrzanów, PL: Wed 15 Jul — Scattered clouds, 18–18°C",
      "content_html": "<p><strong>Scattered clouds</strong> · High 18°C · Low 18°C</p>\n<ul>\n<li>Chance of precipitation: 0%</li>\n<li>Feels like (midday): 18°C</li>\n<li>Wind: up to 0.1 m/s</li>\n<li>Humidity: 83%</li>\n</ul>\n<p><em>Partial day (forecast window does not cover all hours).</em></p>",
      "date_published": "2026-07-14T22:00:00Z",
      "date_modified": "2026-07-15T19:16:26Z",
      "tags": [
        "weather"
      ]
    },
    {
      "id": "urn:openweather:chrzanów-pl:2026-07-14",
      "url": "https://openweathermap.org/city/3101547",
      "title": "Chrzanów, PL: Tue 14 Jul — Light rain, 19–19°C",
      "content_html": "<p><strong>Light rain</strong> · High 19°C · Low 19°C</p>\n<ul>\n<li>Chance of precipitation: 59%</li>\n<li>Feels like (midday): 19°C</li>\n<li>Wind: up to 4.5 m/s</li>\n<li>Humidity: 86%</li>\n<li>Rain: 0.3 mm</li>\n</ul>\n<p><em>Partial day (forecast window does not cover all hours).</em></p>",
      "date_published": "2026-07-13T22:00:00Z",
      "date_modified": "2026-07-14T19:24:30Z",
      "tags": [
        "weather"
      ]
    },
    {
      "id": "urn:openweather:chrzanów-pl:2026-07-13",
      "url": "https://openweathermap.org/city/3101547",
      "title": "Chrzanów, PL: Mon 13 Jul — Light rain, 18–18°C",
      "content_html": "<p><strong>Light rain</strong> · High 18°C · Low 18°C</p>\n<ul>\n<li>Chance of precipitation: 100%</li>\n<li>Feels like (midday): 18°C</li>\n<li>Wind: up to 1.1 m/s</li>\n<li>Humidity: 86%</li>\n<li>Rain: 1.2 mm</li>\n</ul>\n<p><em>Partial day (forecast window does not cover all hours).</em></p>",
      "date_published": "2026-07-12T22:00:00Z",
      "date_modified": "2026-07-13T19:28:58Z",
      "tags": [
        "weather"
      ]
    },
    {
      "id": "urn:openweather:chrzanów-pl:2026-07-12",
      "url": "https://openweathermap.org/city/3101547",
      "title": "Chrzanów, PL: Sun 12 Jul — Light rain, 17–17°C",
      "content_html": "<p><strong>Light rain</strong> · High 17°C · Low 17°C</p>\n<ul>\n<li>Chance of precipitation: 20%</li>\n<li>Feels like (midday): 17°C</li>\n<li>Wind: up to 1.2 m/s</li>\n<li>Humidity: 93%</li>\n<li>Rain: 0.1 mm</li>\n</ul>\n<p><em>Partial day (forecast window does not cover all hours).</em></p>",
      "date_published": "2026-07-11T22:00:00Z",
      "date_modified": "2026-07-12T20:54:06Z",
      "tags": [
        "weather"
      ]
    },
    {
      "id": "urn:openweather:chrzanów-pl:2026-07-11",
      "url": "https://openweathermap.org/city/3101547",
      "title": "Chrzanów, PL: Sat 11 Jul — Broken clouds, 17–17°C",
      "content_html": "<p><strong>Broken clouds</strong> · High 17°C · Low 17°C</p>\n<ul>\n<li>Chance of precipitation: 0%</li>\n<li>Feels like (midday): 16°C</li>\n<li>Wind: up to 1.0 m/s</li>\n<li>Humidity: 81%</li>\n</ul>\n<p><em>Partial day (forecast window does not cover all hours).</em></p>",
      "date_published": "2026-07-10T22:00:00Z",
      "date_modified": "2026-07-11T20:52:54Z",
      "tags": [
        "weather"
      ]
    },
    {
      "id": "urn:openweather:chrzanów-pl:2026-07-10",
      "url": "https://openweathermap.org/city/3101547",
      "title": "Chrzanów, PL: Fri 10 Jul — Overcast clouds, 17–17°C",
      "content_html": "<p><strong>Overcast clouds</strong> · High 17°C · Low 17°C</p>\n<ul>\n<li>Chance of precipitation: 0%</li>\n<li>Feels like (midday): 17°C</li>\n<li>Wind: up to 2.1 m/s</li>\n<li>Humidity: 84%</li>\n</ul>\n<p><em>Partial day (forecast window does not cover all hours).</em></p>",
      "date_published": "2026-07-09T22:00:00Z",
      "date_modified": "2026-07-10T19:32:29Z",
      "tags": [
        "weather"
      ]
    },
    {
      "id": "urn:openweather:chrzanów-pl:2026-07-09",
      "url": "https://openweathermap.org/city/3101547",
      "title": "Chrzanów, PL: Thu 09 Jul — Light rain, 12–12°C",
      "content_html": "<p><strong>Light rain</strong> · High 12°C · Low 12°C</p>\n<ul>\n<li>Chance of precipitation: 31%</li>\n<li>Feels like (midday): 11°C</li>\n<li>Wind: up to 2.5 m/s</li>\n<li>Humidity: 79%</li>\n<li>Rain: 0.1 mm</li>\n</ul>\n<p><em>Partial day (forecast window does not cover all hours).</em></p>",
      "date_published": "2026-07-08T22:00:00Z",
      "date_modified": "2026-07-09T20:00:28Z",
      "tags": [
        "weather"
      ]
    },
    {
      "id": "urn:openweather:chrzanów-pl:2026-07-08",
      "url": "https://openweathermap.org/city/3101547",
      "title": "Chrzanów, PL: Wed 08 Jul — Broken clouds, 16–16°C",
      "content_html": "<p><strong>Broken clouds</strong> · High 16°C · Low 16°C</p>\n<ul>\n<li>Chance of precipitation: 0%</li>\n<li>Feels like (midday): 15°C</li>\n<li>Wind: up to 3.4 m/s</li>\n<li>Humidity: 61%</li>\n</ul>\n<p><em>Partial day (forecast window does not cover all hours).</em></p>",
      "date_published": "2026-07-07T22:00:00Z",
      "date_modified": "2026-07-08T19:30:16Z",
      "tags": [
        "weather"
      ]
    },
    {
      "id": "urn:openweather:chrzanów-pl:2026-07-07",
      "url": "https://openweathermap.org/city/3101547",
      "title": "Chrzanów, PL: Tue 07 Jul — Light rain, 18–18°C",
      "content_html": "<p><strong>Light rain</strong> · High 18°C · Low 18°C</p>\n<ul>\n<li>Chance of precipitation: 37%</li>\n<li>Feels like (midday): 18°C</li>\n<li>Wind: up to 5.5 m/s</li>\n<li>Humidity: 84%</li>\n<li>Rain: 0.3 mm</li>\n</ul>\n<p><em>Partial day (forecast window does not cover all hours).</em></p>",
      "date_published": "2026-07-06T22:00:00Z",
      "date_modified": "2026-07-07T18:03:54Z",
      "tags": [
        "weather"
      ]
    },
    {
      "id": "urn:openweather:chrzanów-pl:2026-07-06",
      "url": "https://openweathermap.org/city/3101547",
      "title": "Chrzanów, PL: Mon 06 Jul — Light rain, 18–18°C",
      "content_html": "<p><strong>Light rain</strong> · High 18°C · Low 18°C</p>\n<ul>\n<li>Chance of precipitation: 20%</li>\n<li>Feels like (midday): 18°C</li>\n<li>Wind: up to 2.9 m/s</li>\n<li>Humidity: 87%</li>\n<li>Rain: 0.1 mm</li>\n</ul>\n<p><em>Partial day (forecast window does not cover all hours).</em></p>",
      "date_published": "2026-07-05T22:00:00Z",
      "date_modified": "2026-07-06T20:02:19Z",
      "tags": [
        "weather"
      ]
    },
    {
      "id": "urn:openweather:chrzanów-pl:2026-07-05",
      "url": "https://openweathermap.org/city/3101547",
      "title": "Chrzanów, PL: Sun 05 Jul — Light rain, 17–17°C",
      "content_html": "<p><strong>Light rain</strong> · High 17°C · Low 17°C</p>\n<ul>\n<li>Chance of precipitation: 100%</li>\n<li>Feels like (midday): 17°C</li>\n<li>Wind: up to 2.5 m/s</li>\n<li>Humidity: 89%</li>\n<li>Rain: 0.8 mm</li>\n</ul>\n<p><em>Partial day (forecast window does not cover all hours).</em></p>",
      "date_published": "2026-07-04T22:00:00Z",
      "date_modified": "2026-07-05T19:01:38Z",
      "tags": [
        "weather"
      ]
    },
    {
      "id": "urn:openweather:chrzanów-pl:2026-07-04",
      "url": "https://openweathermap.org/city/3101547",
      "title": "Chrzanów, PL: Sat 04 Jul — Scattered clouds, 18–18°C",
      "content_html": "<p><strong>Scattered clouds</strong> · High 18°C · Low 18°C</p>\n<ul>\n<li>Chance of precipitation: 0%</li>\n<li>Feels like (midday): 18°C</li>\n<li>Wind: up to 2.5 m/s</li>\n<li>Humidity: 66%</li>\n</ul>\n<p><em>Partial day (forecast window does not cover all hours).</em></p>",
      "date_published": "2026-07-03T22:00:00Z",
      "date_modified": "2026-07-04T19:19:07Z",
      "tags": [
        "weather"
      ]
    },
    {
      "id": "urn:openweather:chrzanów-pl:2026-07-03",
      "url": "https://openweathermap.org/city/3101547",
      "title": "Chrzanów, PL: Fri 03 Jul — Clear sky, 17–17°C",
      "content_html": "<p><strong>Clear sky</strong> · High 17°C · Low 17°C</p>\n<ul>\n<li>Chance of precipitation: 0%</li>\n<li>Feels like (midday): 17°C</li>\n<li>Wind: up to 3.0 m/s</li>\n<li>Humidity: 63%</li>\n</ul>\n<p><em>Partial day (forecast window does not cover all hours).</em></p>",
      "date_published": "2026-07-02T22:00:00Z",
      "date_modified": "2026-07-03T19:28:09Z",
      "tags": [
        "weather"
      ]
    },
    {
      "id": "urn:openweather:chrzanów-pl:2026-07-02",
      "url": "https://openweathermap.org/city/3101547",
      "title": "Chrzanów, PL: Thu 02 Jul — Clear sky, 21–21°C",
      "content_html": "<p><strong>Clear sky</strong> · High 21°C · Low 21°C</p>\n<ul>\n<li>Chance of precipitation: 0%</li>\n<li>Feels like (midday): 21°C</li>\n<li>Wind: up to 0.4 m/s</li>\n<li>Humidity: 67%</li>\n</ul>\n<p><em>Partial day (forecast window does not cover all hours).</em></p>",
      "date_published": "2026-07-01T22:00:00Z",
      "date_modified": "2026-07-02T19:28:56Z",
      "tags": [
        "weather"
      ]
    },
    {
      "id": "urn:openweather:chrzanów-pl:2026-07-01",
      "url": "https://openweathermap.org/city/3101547",
      "title": "Chrzanów, PL: Wed 01 Jul — Light rain, 19–19°C",
      "content_html": "<p><strong>Light rain</strong> · High 19°C · Low 19°C</p>\n<ul>\n<li>Chance of precipitation: 24%</li>\n<li>Feels like (midday): 20°C</li>\n<li>Wind: up to 1.4 m/s</li>\n<li>Humidity: 95%</li>\n<li>Rain: 0.2 mm</li>\n</ul>\n<p><em>Partial day (forecast window does not cover all hours).</em></p>",
      "date_published": "2026-06-30T22:00:00Z",
      "date_modified": "2026-07-01T20:00:59Z",
      "tags": [
        "weather"
      ]
    },
    {
      "id": "urn:openweather:chrzanów-pl:2026-06-30",
      "url": "https://openweathermap.org/city/3101547",
      "title": "Chrzanów, PL: Tue 30 Jun — Light rain, 25–25°C",
      "content_html": "<p><strong>Light rain</strong> · High 25°C · Low 25°C</p>\n<ul>\n<li>Chance of precipitation: 75%</li>\n<li>Feels like (midday): 25°C</li>\n<li>Wind: up to 3.6 m/s</li>\n<li>Humidity: 77%</li>\n<li>Rain: 0.4 mm</li>\n</ul>\n<p><em>Partial day (forecast window does not cover all hours).</em></p>",
      "date_published": "2026-06-29T22:00:00Z",
      "date_modified": "2026-06-30T20:06:51Z",
      "tags": [
        "weather"
      ]
    },
    {
      "id": "urn:openweather:chrzanów-pl:2026-06-29",
      "url": "https://openweathermap.org/city/3101547",
      "title": "Chrzanów, PL: Mon 29 Jun — Light rain, 27–27°C",
      "content_html": "<p><strong>Light rain</strong> · High 27°C · Low 27°C</p>\n<ul>\n<li>Chance of precipitation: 26%</li>\n<li>Feels like (midday): 27°C</li>\n<li>Wind: up to 2.7 m/s</li>\n<li>Humidity: 58%</li>\n<li>Rain: 0.1 mm</li>\n</ul>\n<p><em>Partial day (forecast window does not cover all hours).</em></p>",
      "date_published": "2026-06-28T22:00:00Z",
      "date_modified": "2026-06-29T18:12:17Z",
      "tags": [
        "weather"
      ]
    },
    {
      "id": "urn:openweather:chrzanów-pl:2026-06-28",
      "url": "https://openweathermap.org/city/3101547",
      "title": "Chrzanów, PL: Sun 28 Jun — Broken clouds, 26–26°C",
      "content_html": "<p><strong>Broken clouds</strong> · High 26°C · Low 26°C</p>\n<ul>\n<li>Chance of precipitation: 0%</li>\n<li>Feels like (midday): 26°C</li>\n<li>Wind: up to 1.8 m/s</li>\n<li>Humidity: 56%</li>\n</ul>\n<p><em>Partial day (forecast window does not cover all hours).</em></p>",
      "date_published": "2026-06-27T22:00:00Z",
      "date_modified": "2026-06-28T19:24:33Z",
      "tags": [
        "weather"
      ]
    },
    {
      "id": "urn:openweather:chrzanów-pl:2026-06-27",
      "url": "https://openweathermap.org/city/3101547",
      "title": "Chrzanów, PL: Sat 27 Jun — Clear sky, 24–24°C",
      "content_html": "<p><strong>Clear sky</strong> · High 24°C · Low 24°C</p>\n<ul>\n<li>Chance of precipitation: 0%</li>\n<li>Feels like (midday): 25°C</li>\n<li>Wind: up to 1.9 m/s</li>\n<li>Humidity: 64%</li>\n</ul>\n<p><em>Partial day (forecast window does not cover all hours).</em></p>",
      "date_published": "2026-06-26T22:00:00Z",
      "date_modified": "2026-06-27T19:26:50Z",
      "tags": [
        "weather"
      ]
    },
    {
      "id": "urn:openweather:chrzanów-pl:2026-06-26",
      "url": "https://openweathermap.org/city/3101547",
      "title": "Chrzanów, PL: Fri 26 Jun — Clear sky, 21–21°C",
      "content_html": "<p><strong>Clear sky</strong> · High 21°C · Low 21°C</p>\n<ul>\n<li>Chance of precipitation: 0%</li>\n<li>Feels like (midday): 21°C</li>\n<li>Wind: up to 1.1 m/s</li>\n<li>Humidity: 51%</li>\n</ul>\n<p><em>Partial day (forecast window does not cover all hours).</em></p>",
      "date_published": "2026-06-25T22:00:00Z",
      "date_modified": "2026-06-26T19:53:04Z",
      "tags": [
        "weather"
      ]
    },
    {
      "id": "urn:openweather:chrzanów-pl:2026-06-25",
      "url": "https://openweathermap.org/city/3101547",
      "title": "Chrzanów, PL: Thu 25 Jun — Scattered clouds, 24–24°C",
      "content_html": "<p><strong>Scattered clouds</strong> · High 24°C · Low 24°C</p>\n<ul>\n<li>Chance of precipitation: 0%</li>\n<li>Feels like (midday): 24°C</li>\n<li>Wind: up to 0.7 m/s</li>\n<li>Humidity: 57%</li>\n</ul>\n<p><em>Partial day (forecast window does not cover all hours).</em></p>",
      "date_published": "2026-06-24T22:00:00Z",
      "date_modified": "2026-06-25T18:13:52Z",
      "tags": [
        "weather"
      ]
    },
    {
      "id": "urn:openweather:chrzanów-pl:2026-06-24",
      "url": "https://openweathermap.org/city/3101547",
      "title": "Chrzanów, PL: Wed 24 Jun — Clear sky, 17–17°C",
      "content_html": "<p><strong>Clear sky</strong> · High 17°C · Low 17°C</p>\n<ul>\n<li>Chance of precipitation: 0%</li>\n<li>Feels like (midday): 16°C</li>\n<li>Wind: up to 1.2 m/s</li>\n<li>Humidity: 61%</li>\n</ul>\n<p><em>Partial day (forecast window does not cover all hours).</em></p>",
      "date_published": "2026-06-23T22:00:00Z",
      "date_modified": "2026-06-24T19:51:49Z",
      "tags": [
        "weather"
      ]
    },
    {
      "id": "urn:openweather:chrzanów-pl:2026-06-23",
      "url": "https://openweathermap.org/city/3101547",
      "title": "Chrzanów, PL: Tue 23 Jun — Broken clouds, 16–16°C",
      "content_html": "<p><strong>Broken clouds</strong> · High 16°C · Low 16°C</p>\n<ul>\n<li>Chance of precipitation: 0%</li>\n<li>Feels like (midday): 16°C</li>\n<li>Wind: up to 1.5 m/s</li>\n<li>Humidity: 71%</li>\n</ul>\n<p><em>Partial day (forecast window does not cover all hours).</em></p>",
      "date_published": "2026-06-22T22:00:00Z",
      "date_modified": "2026-06-23T20:19:26Z",
      "tags": [
        "weather"
      ]
    },
    {
      "id": "urn:openweather:chrzanów-pl:2026-06-22",
      "url": "https://openweathermap.org/city/3101547",
      "title": "Chrzanów, PL: Mon 22 Jun — Light rain, 17–17°C",
      "content_html": "<p><strong>Light rain</strong> · High 17°C · Low 17°C</p>\n<ul>\n<li>Chance of precipitation: 42%</li>\n<li>Feels like (midday): 17°C</li>\n<li>Wind: up to 1.5 m/s</li>\n<li>Humidity: 90%</li>\n<li>Rain: 0.2 mm</li>\n</ul>\n<p><em>Partial day (forecast window does not cover all hours).</em></p>",
      "date_published": "2026-06-21T22:00:00Z",
      "date_modified": "2026-06-22T20:53:39Z",
      "tags": [
        "weather"
      ]
    },
    {
      "id": "urn:openweather:chrzanów-pl:2026-06-21",
      "url": "https://openweathermap.org/city/3101547",
      "title": "Chrzanów, PL: Sun 21 Jun — Light rain, 19–19°C",
      "content_html": "<p><strong>Light rain</strong> · High 19°C · Low 19°C</p>\n<ul>\n<li>Chance of precipitation: 100%</li>\n<li>Feels like (midday): 19°C</li>\n<li>Wind: up to 1.5 m/s</li>\n<li>Humidity: 79%</li>\n<li>Rain: 1.3 mm</li>\n</ul>\n<p><em>Partial day (forecast window does not cover all hours).</em></p>",
      "date_published": "2026-06-20T22:00:00Z",
      "date_modified": "2026-06-21T19:46:13Z",
      "tags": [
        "weather"
      ]
    },
    {
      "id": "urn:openweather:chrzanów-pl:2026-06-20",
      "url": "https://openweathermap.org/city/3101547",
      "title": "Chrzanów, PL: Sat 20 Jun — Light rain, 22–22°C",
      "content_html": "<p><strong>Light rain</strong> · High 22°C · Low 22°C</p>\n<ul>\n<li>Chance of precipitation: 100%</li>\n<li>Feels like (midday): 22°C</li>\n<li>Wind: up to 3.8 m/s</li>\n<li>Humidity: 76%</li>\n<li>Rain: 2.6 mm</li>\n</ul>\n<p><em>Partial day (forecast window does not cover all hours).</em></p>",
      "date_published": "2026-06-19T22:00:00Z",
      "date_modified": "2026-06-20T19:41:37Z",
      "tags": [
        "weather"
      ]
    }
  ]
}
